tensorflow_model_remediation/__init__.py
tensorflow_model_remediation/version.py
tensorflow_model_remediation/common/__init__.py
tensorflow_model_remediation/common/docs.py
tensorflow_model_remediation/common/types.py
tensorflow_model_remediation/counterfactual/__init__.py
tensorflow_model_remediation/counterfactual/api_test.py
tensorflow_model_remediation/counterfactual/keras/__init__.py
tensorflow_model_remediation/counterfactual/keras/models/__init__.py
tensorflow_model_remediation/counterfactual/keras/models/counterfactual_model.py
tensorflow_model_remediation/counterfactual/keras/models/counterfactual_model_test.py
tensorflow_model_remediation/counterfactual/keras/utils/__init__.py
tensorflow_model_remediation/counterfactual/keras/utils/input_utils.py
tensorflow_model_remediation/counterfactual/keras/utils/input_utils_test.py
tensorflow_model_remediation/counterfactual/keras/utils/structure_utils.py
tensorflow_model_remediation/counterfactual/keras/utils/structure_utils_test.py
tensorflow_model_remediation/counterfactual/losses/__init__.py
tensorflow_model_remediation/counterfactual/losses/base_loss.py
tensorflow_model_remediation/counterfactual/losses/base_loss_test.py
tensorflow_model_remediation/counterfactual/losses/loss_utils.py
tensorflow_model_remediation/counterfactual/losses/loss_utils_test.py
tensorflow_model_remediation/counterfactual/losses/pairwise_absolute_difference_loss.py
tensorflow_model_remediation/counterfactual/losses/pairwise_absolute_difference_loss_test.py
tensorflow_model_remediation/counterfactual/losses/pairwise_cosine_loss.py
tensorflow_model_remediation/counterfactual/losses/pairwise_cosine_loss_test.py
tensorflow_model_remediation/counterfactual/losses/pairwise_mse_loss.py
tensorflow_model_remediation/counterfactual/losses/pairwise_mse_loss_test.py
tensorflow_model_remediation/min_diff/__init__.py
tensorflow_model_remediation/min_diff/api_test.py
tensorflow_model_remediation/min_diff/keras/__init__.py
tensorflow_model_remediation-0.1.7.1.dist-info/AUTHORS
tensorflow_model_remediation-0.1.7.1.dist-info/LICENSE
tensorflow_model_remediation-0.1.7.1.dist-info/METADATA
tensorflow_model_remediation-0.1.7.1.dist-info/WHEEL
tensorflow_model_remediation-0.1.7.1.dist-info/top_level.txt
tensorflow_model_remediation-0.1.7.1.dist-info/RECORD
