Metadata-Version: 2.1
Name: tensorflow-model-remediation
Version: 0.1.7.1
Summary: TensorFlow Model Remediation
Home-page: https://github.com/tensorflow/model-remediation
Author: Google LLC
Author-email: packages@tensorflow.org
License: Apache 2.0
Keywords: tensorflow model remediation fairness responsible machine learning
Platform: UNKNOWN
Classifier: Development Status :: 4 - Beta
Classifier: Intended Audience :: Developers
Classifier: Intended Audience :: Education
Classifier: Intended Audience :: Science/Research
Classifier: License :: OSI Approved :: Apache Software License
Classifier: Operating System :: OS Independent
Classifier: Programming Language :: Python :: 3
Classifier: Programming Language :: Python :: 3.6
Classifier: Programming Language :: Python :: 3.7
Classifier: Programming Language :: Python :: 3.8
Classifier: Programming Language :: Python :: 3 :: Only
Classifier: Topic :: Scientific/Engineering
Classifier: Topic :: Scientific/Engineering :: Mathematics
Classifier: Topic :: Scientific/Engineering :: Artificial Intelligence
Classifier: Topic :: Software Development
Classifier: Topic :: Software Development :: Libraries
Classifier: Topic :: Software Development :: Libraries :: Python Modules
Requires-Python: >=3.6,<4
License-File: LICENSE
License-File: AUTHORS
Requires-Dist: dill
Requires-Dist: mock
Requires-Dist: pandas
Requires-Dist: tensorflow-hub
Requires-Dist: tensorflow (>=2.0.0)
